qtpyeditor/__init__.py
qtpyeditor/find_gotoline.py
qtpyeditor/linenumber.py
qtpyeditor/syntaxana.py
qtpyeditor/Utilities/__init__.py
qtpyeditor/Utilities/autocomp.py
qtpyeditor/codeedit/__init__.py
qtpyeditor/codeedit/basecodeedit.py
qtpyeditor/codeedit/pythonedit.py
qtpyeditor/codeeditor/__init__.py
qtpyeditor/codeeditor/abstracteditor.py
qtpyeditor/codeeditor/baseeditor.py
qtpyeditor/codeeditor/pythoneditor.py
qtpyeditor/highlighters/__init__.py
qtpyeditor/highlighters/python.py
qtpyeditor/icons/breakpoint.svg
qtpyeditor/icons/copy.svg
qtpyeditor/icons/debug.svg
qtpyeditor/icons/format.svg
qtpyeditor/icons/help.svg
qtpyeditor/icons/python.svg
qtpyeditor/icons/run.svg
qtpyeditor/icons/save.svg
qtpyeditor/icons/spate.svg
qtpyeditor/icons/autocomp/class.png
qtpyeditor/icons/autocomp/function.png
qtpyeditor/icons/autocomp/instance.png
qtpyeditor/icons/autocomp/keyword.png
qtpyeditor/icons/autocomp/module.png
qtpyeditor/icons/autocomp/param.png
qtpyeditor/icons/autocomp/path.png
qtpyeditor/icons/autocomp/property.png
qtpyeditor/icons/autocomp/statement.png
qtpyeditor/translations/qt_zh_CN.qm
qtpyeditor/translations/qt_zh_CN.ts
qtpyeditor/ui/__init__.py
qtpyeditor/ui/findinpath.py
qtpyeditor/ui/formeditor.py
qtpyeditor/ui/gotoline.py
qtpyeditor/ui/ui_formeditor.py
qtpyeditor/ui/ui_gotoline.py
qtpyeditor-0.2.12.dist-info/LICENSE
qtpyeditor-0.2.12.dist-info/METADATA
qtpyeditor-0.2.12.dist-info/WHEEL
qtpyeditor-0.2.12.dist-info/top_level.txt
qtpyeditor-0.2.12.dist-info/RECORD
